<?xml version="1.0"?>
<Config Version="5">
   <Robot Name="PSM2" NumOfActuator="7" NumOfJoint="7" SN="32204">
      <Actuator ActuatorID="0" AxisID="0" BoardID="8" Type="Revolute">
         <Drive>
            <AmpsToBits Offset="32776" Scale="-5242.88" />
            <BitsToFeedbackAmps Offset="6.245617" Scale="-0.000190738" />
            <NmToAmps Scale="0.404089" />
            <MaxCurrent Unit="A" Value="1.340" />
         </Drive>
         <Encoder>
            <BitsToPosSI Scale="-0.00044248" Unit="deg" />
         </Encoder>
         <AnalogIn>
            <BitsToVolts Offset="0" Scale="6.86656e-05" />
            <VoltsToPosSI Offset="98.954108" Scale="-43.5709949917" Unit="deg" />
         </AnalogIn>
      </Actuator>
      <Actuator ActuatorID="1" AxisID="1" BoardID="8" Type="Revolute">
         <Drive>
            <AmpsToBits Offset="32762" Scale="-5242.88" />
            <BitsToFeedbackAmps Offset="6.237796" Scale="-0.000190738" />
            <NmToAmps Scale="0.404089" />
            <MaxCurrent Unit="A" Value="1.340" />
         </Drive>
         <Encoder>
            <BitsToPosSI Scale="-0.00044248" Unit="deg" />
         </Encoder>
         <AnalogIn>
            <BitsToVolts Offset="0" Scale="6.86656e-05" />
            <VoltsToPosSI Offset="65.033976" Scale="-28.9499186003" Unit="deg" />
         </AnalogIn>
      </Actuator>
      <Actuator ActuatorID="2" AxisID="2" BoardID="8" Type="Prismatic">
         <Drive>
            <AmpsToBits Offset="32834" Scale="5242.88" />
            <BitsToFeedbackAmps Offset="-6.252684" Scale="0.000190738" />
            <NmToAmps Scale="0.067828" />
            <MaxCurrent Unit="A" Value="0.670" />
         </Drive>
         <Encoder>
            <BitsToPosSI Scale="0.00129629" Unit="mm" />
         </Encoder>
         <AnalogIn>
            <BitsToVolts Offset="0" Scale="6.86656e-05" />
            <VoltsToPosSI Offset="-7.779003" Scale="58.9906493614" Unit="mm" />
         </AnalogIn>
      </Actuator>
      <Actuator ActuatorID="3" AxisID="3" BoardID="8" Type="Revolute">
         <Drive>
            <AmpsToBits Offset="32840" Scale="-5242.88" />
            <BitsToFeedbackAmps Offset="6.233475" Scale="-0.000190738" />
            <NmToAmps Scale="1.949705" />
            <MaxCurrent Unit="A" Value="0.670" />
         </Drive>
         <Encoder>
            <BitsToPosSI Scale="-0.00768574" Unit="deg" />
         </Encoder>
         <AnalogIn>
            <BitsToVolts Offset="0" Scale="6.86656e-05" />
            <VoltsToPosSI Offset="178.425887348" Scale="-79.3591563635" Unit="deg" />
         </AnalogIn>
      </Actuator>
      <Actuator ActuatorID="4" AxisID="0" BoardID="9" Type="Revolute">
         <Drive>
            <AmpsToBits Offset="32977" Scale="-5242.88" />
            <BitsToFeedbackAmps Offset="6.253045" Scale="-0.000190738" />
            <NmToAmps Scale="1.949705" />
            <MaxCurrent Unit="A" Value="0.670" />
         </Drive>
         <Encoder>
            <BitsToPosSI Offset="0" Scale="-0.00768574" Unit="deg" />
         </Encoder>
         <AnalogIn>
            <BitsToVolts Offset="0" Scale="6.86656e-05" />
            <VoltsToPosSI Offset="176.925724172" Scale="-78.6335220041" Unit="deg" />
         </AnalogIn>
      </Actuator>
      <Actuator ActuatorID="5" AxisID="1" BoardID="9" Type="Revolute">
         <Drive>
            <AmpsToBits Offset="32865" Scale="5242.88" />
            <BitsToFeedbackAmps Offset="-6.264711" Scale="0.000190738" />
            <NmToAmps Scale="1.949705" />
            <MaxCurrent Unit="A" Value="0.670" />
         </Drive>
         <Encoder>
            <BitsToPosSI Scale="0.00768574" Unit="deg" />
         </Encoder>
         <AnalogIn>
            <BitsToVolts Offset="0" Scale="6.86656e-05" />
            <VoltsToPosSI Offset="177.182220386" Scale="-79.0732795354" Unit="deg" />
         </AnalogIn>
      </Actuator>
      <Actuator ActuatorID="6" AxisID="2" BoardID="9" Type="Revolute">
         <Drive>
            <AmpsToBits Offset="32932" Scale="5242.88" />
            <BitsToFeedbackAmps Offset="-6.258423" Scale="0.000190738" />
            <NmToAmps Scale="1.949705" />
            <MaxCurrent Unit="A" Value="0.670" />
         </Drive>
         <Encoder>
            <BitsToPosSI Scale="0.00768574" Unit="deg" />
         </Encoder>
         <AnalogIn>
            <BitsToVolts Offset="0" Scale="6.86656e-05" />
            <VoltsToPosSI Offset="177.626962638" Scale="-78.940917432" Unit="deg" />
         </AnalogIn>
      </Actuator>
      <Potentiometers Position="Actuators">
	<Tolerance Axis="0" Distance="5.0" Latency="0.01" Unit="deg" />
	<Tolerance Axis="1" Distance="5.0" Latency="0.01" Unit="deg" />
	<Tolerance Axis="2" Distance="5.0" Latency="0.01" Unit="mm" />
	<Tolerance Axis="3" Distance="25.0" Latency="0.05" Unit="deg" />
	<Tolerance Axis="4" Distance="25.0" Latency="0.05" Unit="deg" />
	<Tolerance Axis="5" Distance="25.0" Latency="0.05" Unit="deg" />
	<Tolerance Axis="6" Distance="25.0" Latency="0.05" Unit="deg" />
      </Potentiometers>
   </Robot>
   <DigitalIn BitID="0" BoardID="8" Debounce="0.2" Name="PSM2-SUJClutch" Pressed="1" Trigger="all"/>
   <DigitalIn BitID="2" BoardID="8" Debounce="0.2" Name="PSM2-ManipClutch" Pressed="1" Trigger="all"/>
   <DigitalIn BitID="7" BoardID="9" Debounce="1.5" Name="PSM2-Tool" Pressed="1" Trigger="all"/>
   <DigitalIn BitID="10" BoardID="9" Debounce="1.5" Name="PSM2-Adapter" Pressed="1" Trigger="all"/>
   <DallasChip BoardID="9" Name="PSM2-Dallas"/>
</Config>
